wandelbots_isaacsim_api/__init__.py
wandelbots_isaacsim_api/api_client.py
wandelbots_isaacsim_api/api_response.py
wandelbots_isaacsim_api/configuration.py
wandelbots_isaacsim_api/exceptions.py
wandelbots_isaacsim_api/py.typed
wandelbots_isaacsim_api/rest.py
wandelbots_isaacsim_api/api/__init__.py
wandelbots_isaacsim_api/api/collision_world_api.py
wandelbots_isaacsim_api/api/default_api.py
wandelbots_isaacsim_api/api/manipulators_motion_group_api.py
wandelbots_isaacsim_api/api/periphery_camera_api.py
wandelbots_isaacsim_api/api/prims_api.py
wandelbots_isaacsim_api/api/stage_api.py
wandelbots_isaacsim_api/api/teaching_api.py
wandelbots_isaacsim_api/api/trajectory_api.py
wandelbots_isaacsim_api/api/ui_api.py
wandelbots_isaacsim_api/collision/__init__.py
wandelbots_isaacsim_api/collision/utils.py
wandelbots_isaacsim_api/models/__init__.py
wandelbots_isaacsim_api/models/auth0_credentials.py
wandelbots_isaacsim_api/models/body_apply_relative_pose.py
wandelbots_isaacsim_api/models/body_set_joint_state.py
wandelbots_isaacsim_api/models/body_set_prim_metadata.py
wandelbots_isaacsim_api/models/body_set_prim_visibility.py
wandelbots_isaacsim_api/models/body_set_semantic_label.py
wandelbots_isaacsim_api/models/body_update_colliders.py
wandelbots_isaacsim_api/models/body_update_pose.py
wandelbots_isaacsim_api/models/bounding_box2_d.py
wandelbots_isaacsim_api/models/bounding_box3_d.py
wandelbots_isaacsim_api/models/box.py
wandelbots_isaacsim_api/models/box_sweep_parameters.py
wandelbots_isaacsim_api/models/capsule.py
wandelbots_isaacsim_api/models/collider.py
wandelbots_isaacsim_api/models/color.py
wandelbots_isaacsim_api/models/convex_hull.py
wandelbots_isaacsim_api/models/create_ghost_object.py
wandelbots_isaacsim_api/models/custom_prim.py
wandelbots_isaacsim_api/models/custom_prim_data.py
wandelbots_isaacsim_api/models/cylinder.py
wandelbots_isaacsim_api/models/ghost_object.py
wandelbots_isaacsim_api/models/ghost_object_source.py
wandelbots_isaacsim_api/models/gizmo_prim.py
wandelbots_isaacsim_api-2.10.1.dist-info/licenses/LICENSE
wandelbots_isaacsim_api-2.10.1.dist-info/METADATA
wandelbots_isaacsim_api-2.10.1.dist-info/WHEEL
wandelbots_isaacsim_api-2.10.1.dist-info/top_level.txt
wandelbots_isaacsim_api-2.10.1.dist-info/RECORD
