Metadata-Version: 2.4
Name: wandelbots-isaacsim-api
Version: 2.10.1
Summary: Wandelbots Omniservice
Home-page: 
Author: OpenAPI Generator community
Author-email: team@openapitools.org
Keywords: OpenAPI,OpenAPI-Generator,Wandelbots Omniservice
License-File: LICENSE
Requires-Dist: urllib3<3.0.0,>=1.25.3
Requires-Dist: python-dateutil>=2.8.2
Requires-Dist: aiohttp>=3.8.4
Requires-Dist: aiohttp-retry>=2.8.3
Requires-Dist: pydantic>=2
Requires-Dist: typing-extensions>=4.7.1
Dynamic: author
Dynamic: author-email
Dynamic: description
Dynamic: description-content-type
Dynamic: keywords
Dynamic: license-file
Dynamic: requires-dist
Dynamic: summary
